{
  "id": "political-geography-2026-04-13",
  "journal": "Political Geography",
  "volume": "128",
  "issue": "",
  "date": "2026-04-13",
  "coverImage": {
    "url": "",
    "credit": ""
  },
  "coverStory": {
    "title": {
      "zh": "跨越國界的政治熱情：為何移民積極參與母國政黨？",
      "en": "Transnational Political Passion: Why Migrants Engage in Homeland Party Activities"
    },
    "summary": {
      "zh": "【總結】\n這項研究探討了移民為何積極參與母國政黨的跨國政治活動，發現移民的動機不僅包含政治理想與情感連結，還受到選舉制度和政黨海外存在的深刻影響。研究突破點在於揭示了跨國背景如何重塑傳統的政黨參與動機機制，並首次系統性地比較了拉丁美洲三國（玻利維亞、厄瓜多爾、秘魯）在西班牙巴塞隆納的移民政黨活動分子。這項研究填補了移民政治研究中對高強度政黨活動動機的認知空白，為理解全球化時代的國家與僑民關係提供了新視角。\n\n【研究問題】\n過去研究多關注移民投票和政黨海外聯繫，卻忽略了移民成為政黨積極分子的動機問題。本文旨在解釋：為何移民願意投入時間與資源參與母國政黨活動？這些動機如何在不同跨國背景下變化？為什麼解決這個問題至關重要？因為移民政黨活動分子是維繫跨國政黨活動的核心力量，但他們的參與動機尚未系統研究，這使我們難以理解跨國政治參與的完整圖景，也難以設計更有效的國家-僑民政治互動機制。\n\n【研究方法】\n研究者採用比較案例研究方法，在西班牙巴塞隆納進行深入的民族誌田野調查，訪談了36名來自玻利維亞、厄瓜多爾和秘魯的政黨活動分子（共62次訪談）。研究設計包含四個關鍵步驟：首先，建立概念框架，整合政黨成員參與理論與跨國主義文獻；其次，進行系統性的政策文件與媒體分析；第三，進行參與式觀察，記錄政黨活動與政治事件；最後，分析216名秘魯候選人的履歷，評估移民的政治職業機會。研究方法創新之處在於將選舉制度設計作為解釋變量，分析不同國家的選舉制度如何影響移民的政治參與動機與機會。\n\n【結果】\n研究發現，移民政黨活動分子的動機主要分為四類：政治動機（約佔主導地位，希望影響母國政策或移民政策）、情感動機（對政黨領袖的認同、愛國情緒利他主義）、職涯動機（較為選擇性，尤其在厄瓜多爾因設有海外議席而更明顯）和社交動機（較不突出）。關鍵發現包括：厄瓜多爾因為設有海外議席，移民參與者的職涯動機最強；玻利維亞因禁止海外候選，職涯動機最弱；所有國家的移民都面臨嚴重的資源限制，迫使個人承擔參與成本；跨國政治環境重塑了傳統動機機制，情感連結因領袖個人魅力而加強，政治動機因雙重政治參與（母國與居住國）而複雜化。這些發現對理解全球化背景下國家與僑民的政治關係具有重要意義，為設計更有效的跨國政治參與機制提供了基礎。",
      "en": "**Summary:** \nThis research explores why migrants engage in transnational party activism from their country of origin, revealing that motivations encompass not just political ideals and emotional connections, but are profoundly shaped by electoral systems and parties' overseas presence. The breakthrough lies in demonstrating how the transnational context reshapes traditional mechanisms of party participation motivations, and systematically comparing party activists from three Latin American countries (Bolivia, Ecuador, Peru) in Barcelona, Spain. This study fills a critical gap in migration scholarship by examining high-intensity party activism motivations, offering new perspectives on understanding state-diaspora political relations in an era of globalization.\n\n**Problem:**\nPrevious research has largely examined emigrant voting and party outreach while overlooking the motivations that drive emigrants to become party activists. This article addresses: Why do migrants dedicate time and resources to transnational party activities? How do these motivations vary across different transnational contexts? Why is this crucial? Because emigrant party activists sustain transnational party activities, yet their participation motivations remain understudied, preventing us from understanding the full picture of transnational political participation and designing more effective state-diaspora political interaction mechanisms.\n\n**Approach:**\nThe researcher employed a comparative case study approach, conducting intensive ethnographic fieldwork in Barcelona, Spain, interviewing 36 party activists from Bolivia, Ecuador, and Peru (totaling 62 interviews). The methodology included four key steps: first, developing a conceptual framework integrating party membership theory with transnationalism literature; second, conducting systematic policy document and media analysis; third, performing participant observation of party activities and political events; finally, analyzing the CVs of 216 Peruvian candidates to assess emigrants' access to political careers. The methodological innovation lies in treating electoral system design as an explanatory variable, analyzing how different countries' electoral systems affect migrants' political participation motivations and opportunities.\n\n**Results:**\nFindings reveal four main motivation categories among transnational party activists: political motivations (predominant, aiming to influence homeland or emigrant policies), emotional motivations (identification with party leaders, patriotism, altruism), career motivations (more selective, especially strong in Ecuador due to overseas parliamentary seats), and socializing motivations (less prominent). Key discoveries include: Ecuadorian activists showed strongest career motivations due to reserved parliamentary seats; Bolivian activists exhibited weakest career motivations as emigrant candidacy is prohibited; all migrants faced substantial resource constraints, shifting participation costs onto individuals; the transnational context reshaped traditional mechanisms, with emotional connections strengthened by leader charisma and political motivations complicated by dual political participation (homeland and residence countries). These findings have significant implications for understanding state-diaspora political relations in globalization and provide foundations for designing more effective transnational political participation mechanisms."
    },
    "keyArticle": {
      "title": "Transnational party activism: why do migrants become active in political parties from their country of origin?",
      "authors": [
        "Nicolas Fliess"
      ],
      "doi": "10.1016/j.polgeo.2026.103554",
      "pages": "103554"
    },
    "images": [],
    "links": {
      "official": "https://doi.org/10.1016/j.polgeo.2026.103554",
      "doi": "https://doi.org/10.1016/j.polgeo.2026.103554"
    }
  },
  "_meta": {
    "summary_mode": "full-text",
    "created_at": "2026-05-31T20:10:30.396021+00:00",
    "source": "openalex"
  }
}
